interva/__init__.py
interva/__version__.py
interva/exceptions.py
interva/interva5.py
interva/utils.py
interva/data/causetext.py
interva/data/probbase.xls
interva/data/probbaseV5_19.csv
interva/data/randomva5.csv
interva-1.0.0.dist-info/LICENSE
interva-1.0.0.dist-info/METADATA
interva-1.0.0.dist-info/WHEEL
interva-1.0.0.dist-info/top_level.txt
interva-1.0.0.dist-info/RECORD
