Metadata-Version: 2.1
Name: interva
Version: 1.0.0
Summary: Python implementation of the InterVA Algorithm.
Author-email: Sherry Zhao <zhao.3248@buckeyemail.osu.edu>, Jason Thomas <jarathomas@gmail.com>
Maintainer-email: openVA Team <help@openva.net>
License: GPLv3
Project-URL: Homepage, https://github.com/verbal-autopsy-software/interva
Project-URL: Bug Tracker, https://github.com/verbal-autopsy-software/interva/issues
Keywords: verbal autopsy
Classifier: Programming Language :: Python :: 3
Classifier: Programming Language :: Python :: 3.8
Classifier: Programming Language :: Python :: 3.9
Classifier: Programming Language :: Python :: 3.10
Classifier: Programming Language :: Python :: 3.11
Classifier: Programming Language :: Python :: 3.12
Classifier: License :: OSI Approved :: GNU General Public License v3 (GPLv3)
Classifier: Operating System :: OS Independent
Requires-Python: >=3.8
License-File: LICENSE
Requires-Dist: pandas
Requires-Dist: numpy
Requires-Dist: vacheck>=0.0.3
Requires-Dist: xlrd
